CHANGELOG.txt
LICENSE.txt
MANIFEST.in
README.txt
setup.py
enginetool/__init__.py
enginetool.egg-info/PKG-INFO
enginetool.egg-info/SOURCES.txt
enginetool.egg-info/dependency_links.txt
enginetool.egg-info/requires.txt
enginetool.egg-info/top_level.txt