Metadata-Version: 2.1
Name: enginetool
Version: 0.0.3
Summary: A tool to run calculations about an engine
Home-page: UNKNOWN
Author: Jonathon Gruener
Author-email: jonathon14gruener@gmail.com
License: MIT
Keywords: engine
Platform: UNKNOWN
Classifier: Development Status :: 5 - Production/Stable
Classifier: Intended Audience :: Education
Classifier: Operating System :: Microsoft :: Windows :: Windows 10
Classifier: License :: OSI Approved :: MIT License
Classifier: Programming Language :: Python :: 3
License-File: LICENSE.txt
